{
  "uuid": "d6ab3ae4-d6bb-470c-98e0-9051fec378e9",
  "lastMigration": 22,
  "name": "DTRP",
  "endpointPrefix": "api/v1",
  "latency": 0,
  "port": 3001,
  "hostname": "0.0.0.0",
  "routes": [
    {
      "uuid": "55c2cfa8-1cdf-4417-81ef-3433b15bd8f9",
      "documentation": "",
      "method": "get",
      "endpoint": "vacancies",
      "responses": [
        {
          "uuid": "ddcac502-5eb0-421f-8819-b91d6a65dcc8",
          "body": "{\r\n    \"current_page\": 1,\r\n    \"data\": [\r\n        {\r\n            \"id\": \"1\",\r\n            \"opening_at\": \"2017-01-21 07:44:26\",\r\n            \"description\": \"Omnis fuga sed qui quisquam facere. Qui modi voluptatibus aut beatae dolorem adipisci voluptatem. Explicabo quis corrupti et officia non architecto. Rerum quas sed asperiores vel.\",\r\n            \"role_id\": \"1\",\r\n            \"role\": {\r\n                \"id\": \"1\",\r\n                \"name\": \"Senior Software Programmer - Backend Engineer\",\r\n                \"code\": \"SRBE\",\r\n                \"division_id\": \"1\"\r\n            }\r\n        },\r\n        {\r\n            \"id\": \"2\",\r\n            \"opening_at\": \"1979-07-29 01:35:54\",\r\n            \"description\": \"Quia doloremque natus et quia. Non et consequatur voluptatem nihil ut ut nemo. Distinctio ratione enim est explicabo consequuntur nihil.\",\r\n            \"role_id\": \"2\",\r\n            \"role\": {\r\n                \"id\": \"2\",\r\n                \"name\": \"Junior Software Programmer - Backend Engineer\",\r\n                \"code\": \"JRBE\",\r\n                \"division_id\": \"1\"\r\n            }\r\n        },\r\n        {\r\n            \"id\": \"3\",\r\n            \"opening_at\": \"1975-09-14 05:24:51\",\r\n            \"description\": \"Id aliquid voluptas incidunt. Rem praesentium exercitationem molestiae quod facilis neque.\",\r\n            \"role_id\": \"3\",\r\n            \"role\": {\r\n                \"id\": \"3\",\r\n                \"name\": \"QA Engineer\",\r\n                \"code\": \"QAE\",\r\n                \"division_id\": \"1\"\r\n            }\r\n        },\r\n        {\r\n            \"id\": \"4\",\r\n            \"opening_at\": \"1979-01-26 12:54:39\",\r\n            \"description\": \"Minima repudiandae necessitatibus alias et. Doloribus suscipit velit voluptas dignissimos. Facilis rerum tenetur consequatur deserunt totam omnis.\",\r\n            \"role_id\": \"4\",\r\n            \"role\": {\r\n                \"id\": \"4\",\r\n                \"name\": \"QA Analyst\",\r\n                \"code\": \"QAA\",\r\n                \"division_id\": \"1\"\r\n            }\r\n        },\r\n        {\r\n            \"id\": \"5\",\r\n            \"opening_at\": \"1989-10-02 12:30:13\",\r\n            \"description\": \"Voluptas quis qui ut repellendus totam. Voluptas culpa illo qui. Laborum asperiores veniam neque vel beatae.\",\r\n            \"role_id\": \"5\",\r\n            \"role\": {\r\n                \"id\": \"5\",\r\n                \"name\": \"DevOps/SRE Engineer\",\r\n                \"code\": \"DEVOPS\",\r\n                \"division_id\": \"1\"\r\n            }\r\n        }\r\n    ],\r\n    \"first_page_url\": \"http://localhost:8088/api/v1/vacancies?page=1\",\r\n    \"from\": 1,\r\n    \"last_page\": 5,\r\n    \"last_page_url\": \"http://localhost:8088/api/v1/vacancies?page=5\",\r\n    \"links\": [],\r\n    \"next_page_url\": \"http://localhost:8088/api/v1/vacancies?page=2\",\r\n    \"path\": \"http://localhost:8088/api/v1/vacancies\",\r\n    \"per_page\": 5,\r\n    \"prev_page_url\": null,\r\n    \"to\": 5,\r\n    \"total\": 21\r\n}",
          "latency": 0,
          "statusCode": 200,
          "label": "",
          "headers": [],
          "filePath": "",
          "sendFileAsBody": false,
          "rules": [],
          "rulesOperator": "OR",
          "disableTemplating": false,
          "fallbackTo404": false,
          "default": true
        },
        {
          "uuid": "b858465d-51ae-4013-a35c-7d23cea55b83",
          "body": "{\r\n    \"current_page\": 1,\r\n    \"data\": [\r\n        {\r\n            \"id\": \"1\",\r\n            \"opening_at\": \"2017-01-21 07:44:26\",\r\n            \"description\": \"Omnis fuga sed qui quisquam facere. Qui modi voluptatibus aut beatae dolorem adipisci voluptatem. Explicabo quis corrupti et officia non architecto. Rerum quas sed asperiores vel.\",\r\n            \"role_id\": \"1\",\r\n            \"role\": {\r\n                \"id\": \"1\",\r\n                \"name\": \"Senior Software Programmer - Backend Engineer\",\r\n                \"code\": \"SRBE\",\r\n                \"division_id\": \"1\"\r\n            }\r\n        },\r\n        {\r\n            \"id\": \"2\",\r\n            \"opening_at\": \"1979-07-29 01:35:54\",\r\n            \"description\": \"Quia doloremque natus et quia. Non et consequatur voluptatem nihil ut ut nemo. Distinctio ratione enim est explicabo consequuntur nihil.\",\r\n            \"role_id\": \"2\",\r\n            \"role\": {\r\n                \"id\": \"2\",\r\n                \"name\": \"Junior Software Programmer - Backend Engineer\",\r\n                \"code\": \"JRBE\",\r\n                \"division_id\": \"1\"\r\n            }\r\n        },\r\n        {\r\n            \"id\": \"3\",\r\n            \"opening_at\": \"1975-09-14 05:24:51\",\r\n            \"description\": \"Id aliquid voluptas incidunt. Rem praesentium exercitationem molestiae quod facilis neque.\",\r\n            \"role_id\": \"3\",\r\n            \"role\": {\r\n                \"id\": \"3\",\r\n                \"name\": \"QA Engineer\",\r\n                \"code\": \"QAE\",\r\n                \"division_id\": \"1\"\r\n            }\r\n        },\r\n        {\r\n            \"id\": \"4\",\r\n            \"opening_at\": \"1979-01-26 12:54:39\",\r\n            \"description\": \"Minima repudiandae necessitatibus alias et. Doloribus suscipit velit voluptas dignissimos. Facilis rerum tenetur consequatur deserunt totam omnis.\",\r\n            \"role_id\": \"4\",\r\n            \"role\": {\r\n                \"id\": \"4\",\r\n                \"name\": \"QA Analyst\",\r\n                \"code\": \"QAA\",\r\n                \"division_id\": \"1\"\r\n            }\r\n        },\r\n        {\r\n            \"id\": \"5\",\r\n            \"opening_at\": \"1989-10-02 12:30:13\",\r\n            \"description\": \"Voluptas quis qui ut repellendus totam. Voluptas culpa illo qui. Laborum asperiores veniam neque vel beatae.\",\r\n            \"role_id\": \"5\",\r\n            \"role\": {\r\n                \"id\": \"5\",\r\n                \"name\": \"DevOps/SRE Engineer\",\r\n                \"code\": \"DEVOPS\",\r\n                \"division_id\": \"1\"\r\n            }\r\n        }\r\n    ],\r\n    \"first_page_url\": \"http://localhost:8088/api/v1/vacancies?page=1\",\r\n    \"from\": 1,\r\n    \"last_page\": 5,\r\n    \"last_page_url\": \"http://localhost:8088/api/v1/vacancies?page=5\",\r\n    \"links\": [],\r\n    \"next_page_url\": \"http://localhost:8088/api/v1/vacancies?page=2\",\r\n    \"path\": \"http://localhost:8088/api/v1/vacancies\",\r\n    \"per_page\": 5,\r\n    \"prev_page_url\": null,\r\n    \"to\": 5,\r\n    \"total\": 21\r\n}",
          "latency": 0,
          "statusCode": 200,
          "label": "",
          "headers": [],
          "filePath": "",
          "sendFileAsBody": false,
          "rules": [
            {
              "target": "query",
              "modifier": "page",
              "value": "1",
              "invert": false,
              "operator": "equals"
            }
          ],
          "rulesOperator": "OR",
          "disableTemplating": false,
          "fallbackTo404": false,
          "default": false
        },
        {
          "uuid": "c10e55c3-8845-465a-8f48-8b2e8c15d1bf",
          "body": "{\r\n    \"current_page\": 2,\r\n    \"data\": [\r\n        {\r\n            \"id\": \"6\",\r\n            \"opening_at\": \"2017-01-21 07:44:26\",\r\n            \"description\": \"Omnis fuga sed qui quisquam facere. Qui modi voluptatibus aut beatae dolorem adipisci voluptatem. Explicabo quis corrupti et officia non architecto. Rerum quas sed asperiores vel.\",\r\n            \"role_id\": \"6\",\r\n            \"role\": {\r\n                \"id\": \"6\",\r\n                \"name\": \"Senior Software Programmer - Backend Engineer 2\",\r\n                \"code\": \"SRBE\",\r\n                \"division_id\": \"1\"\r\n            }\r\n        },\r\n        {\r\n            \"id\": \"7\",\r\n            \"opening_at\": \"1979-07-29 01:35:54\",\r\n            \"description\": \"Quia doloremque natus et quia. Non et consequatur voluptatem nihil ut ut nemo. Distinctio ratione enim est explicabo consequuntur nihil.\",\r\n            \"role_id\": \"7\",\r\n            \"role\": {\r\n                \"id\": \"7\",\r\n                \"name\": \"Junior Software Programmer - Backend Engineer 2\",\r\n                \"code\": \"JRBE\",\r\n                \"division_id\": \"1\"\r\n            }\r\n        },\r\n        {\r\n            \"id\": \"8\",\r\n            \"opening_at\": \"1975-09-14 05:24:51\",\r\n            \"description\": \"Id aliquid voluptas incidunt. Rem praesentium exercitationem molestiae quod facilis neque.\",\r\n            \"role_id\": \"8\",\r\n            \"role\": {\r\n                \"id\": \"8\",\r\n                \"name\": \"QA Engineer 2\",\r\n                \"code\": \"QAE\",\r\n                \"division_id\": \"1\"\r\n            }\r\n        },\r\n        {\r\n            \"id\": \"9\",\r\n            \"opening_at\": \"1979-01-26 12:54:39\",\r\n            \"description\": \"Minima repudiandae necessitatibus alias et. Doloribus suscipit velit voluptas dignissimos. Facilis rerum tenetur consequatur deserunt totam omnis.\",\r\n            \"role_id\": \"9\",\r\n            \"role\": {\r\n                \"id\": \"9\",\r\n                \"name\": \"QA Analyst 2\",\r\n                \"code\": \"QAA\",\r\n                \"division_id\": \"1\"\r\n            }\r\n        },\r\n        {\r\n            \"id\": \"10\",\r\n            \"opening_at\": \"1989-10-02 12:30:13\",\r\n            \"description\": \"Voluptas quis qui ut repellendus totam. Voluptas culpa illo qui. Laborum asperiores veniam neque vel beatae.\",\r\n            \"role_id\": \"10\",\r\n            \"role\": {\r\n                \"id\": \"10\",\r\n                \"name\": \"DevOps/SRE Engineer 2\",\r\n                \"code\": \"DEVOPS\",\r\n                \"division_id\": \"1\"\r\n            }\r\n        }\r\n    ],\r\n    \"first_page_url\": \"http://localhost:8088/api/v1/vacancies?page=1\",\r\n    \"from\": 6,\r\n    \"last_page\": 5,\r\n    \"last_page_url\": \"http://localhost:8088/api/v1/vacancies?page=5\",\r\n    \"links\": [],\r\n    \"next_page_url\": \"http://localhost:8088/api/v1/vacancies?page=3\",\r\n    \"path\": \"http://localhost:8088/api/v1/vacancies\",\r\n    \"per_page\": 5,\r\n    \"prev_page_url\": null,\r\n    \"to\": 10,\r\n    \"total\": 21\r\n}",
          "latency": 0,
          "statusCode": 200,
          "label": "",
          "headers": [],
          "filePath": "",
          "sendFileAsBody": false,
          "rules": [
            {
              "target": "query",
              "modifier": "page",
              "value": "2",
              "invert": false,
              "operator": "equals"
            }
          ],
          "rulesOperator": "OR",
          "disableTemplating": false,
          "fallbackTo404": false,
          "default": false
        },
        {
          "uuid": "aadc3570-b921-4571-98a4-fbb92f6abb1d",
          "body": "{\r\n    \"current_page\": 3,\r\n    \"data\": [\r\n        {\r\n            \"id\": \"11\",\r\n            \"opening_at\": \"2017-01-21 07:44:26\",\r\n            \"description\": \"Omnis fuga sed qui quisquam facere. Qui modi voluptatibus aut beatae dolorem adipisci voluptatem. Explicabo quis corrupti et officia non architecto. Rerum quas sed asperiores vel.\",\r\n            \"role_id\": \"11\",\r\n            \"role\": {\r\n                \"id\": \"11\",\r\n                \"name\": \"Senior Software Programmer - Backend Engineer 3\",\r\n                \"code\": \"SRBE\",\r\n                \"division_id\": \"1\"\r\n            }\r\n        },\r\n        {\r\n            \"id\": \"12\",\r\n            \"opening_at\": \"1979-07-29 01:35:54\",\r\n            \"description\": \"Quia doloremque natus et quia. Non et consequatur voluptatem nihil ut ut nemo. Distinctio ratione enim est explicabo consequuntur nihil.\",\r\n            \"role_id\": \"12\",\r\n            \"role\": {\r\n                \"id\": \"12\",\r\n                \"name\": \"Junior Software Programmer - Backend Engineer 3\",\r\n                \"code\": \"JRBE\",\r\n                \"division_id\": \"1\"\r\n            }\r\n        },\r\n        {\r\n            \"id\": \"13\",\r\n            \"opening_at\": \"1975-09-14 05:24:51\",\r\n            \"description\": \"Id aliquid voluptas incidunt. Rem praesentium exercitationem molestiae quod facilis neque.\",\r\n            \"role_id\": \"13\",\r\n            \"role\": {\r\n                \"id\": \"13\",\r\n                \"name\": \"QA Engineer 3\",\r\n                \"code\": \"QAE\",\r\n                \"division_id\": \"1\"\r\n            }\r\n        },\r\n        {\r\n            \"id\": \"14\",\r\n            \"opening_at\": \"1979-01-26 12:54:39\",\r\n            \"description\": \"Minima repudiandae necessitatibus alias et. Doloribus suscipit velit voluptas dignissimos. Facilis rerum tenetur consequatur deserunt totam omnis.\",\r\n            \"role_id\": \"14\",\r\n            \"role\": {\r\n                \"id\": \"14\",\r\n                \"name\": \"QA Analyst 3\",\r\n                \"code\": \"QAA\",\r\n                \"division_id\": \"1\"\r\n            }\r\n        },\r\n        {\r\n            \"id\": \"15\",\r\n            \"opening_at\": \"1989-10-02 12:30:13\",\r\n            \"description\": \"Voluptas quis qui ut repellendus totam. Voluptas culpa illo qui. Laborum asperiores veniam neque vel beatae.\",\r\n            \"role_id\": \"15\",\r\n            \"role\": {\r\n                \"id\": \"15\",\r\n                \"name\": \"DevOps/SRE Engineer 3\",\r\n                \"code\": \"DEVOPS\",\r\n                \"division_id\": \"1\"\r\n            }\r\n        }\r\n    ],\r\n    \"first_page_url\": \"http://localhost:8088/api/v1/vacancies?page=1\",\r\n    \"from\": 11,\r\n    \"last_page\": 5,\r\n    \"last_page_url\": \"http://localhost:8088/api/v1/vacancies?page=5\",\r\n    \"links\": [],\r\n    \"next_page_url\": \"http://localhost:8088/api/v1/vacancies?page=4\",\r\n    \"path\": \"http://localhost:8088/api/v1/vacancies\",\r\n    \"per_page\": 5,\r\n    \"prev_page_url\": null,\r\n    \"to\": 15,\r\n    \"total\": 21\r\n}",
          "latency": 0,
          "statusCode": 200,
          "label": "",
          "headers": [],
          "filePath": "",
          "sendFileAsBody": false,
          "rules": [
            {
              "target": "query",
              "modifier": "page",
              "value": "3",
              "invert": false,
              "operator": "equals"
            }
          ],
          "rulesOperator": "OR",
          "disableTemplating": false,
          "fallbackTo404": false,
          "default": false
        },
        {
          "uuid": "a23203f2-c500-40e6-9b68-49c7836784ac",
          "body": "{\r\n    \"current_page\": 4,\r\n    \"data\": [\r\n        {\r\n            \"id\": \"16\",\r\n            \"opening_at\": \"2017-01-21 07:44:26\",\r\n            \"description\": \"Omnis fuga sed qui quisquam facere. Qui modi voluptatibus aut beatae dolorem adipisci voluptatem. Explicabo quis corrupti et officia non architecto. Rerum quas sed asperiores vel.\",\r\n            \"role_id\": \"16\",\r\n            \"role\": {\r\n                \"id\": \"16\",\r\n                \"name\": \"Senior Software Programmer - Backend Engineer 4\",\r\n                \"code\": \"SRBE\",\r\n                \"division_id\": \"1\"\r\n            }\r\n        },\r\n        {\r\n            \"id\": \"17\",\r\n            \"opening_at\": \"1979-07-29 01:35:54\",\r\n            \"description\": \"Quia doloremque natus et quia. Non et consequatur voluptatem nihil ut ut nemo. Distinctio ratione enim est explicabo consequuntur nihil.\",\r\n            \"role_id\": \"17\",\r\n            \"role\": {\r\n                \"id\": \"17\",\r\n                \"name\": \"Junior Software Programmer - Backend Engineer 4\",\r\n                \"code\": \"JRBE\",\r\n                \"division_id\": \"1\"\r\n            }\r\n        },\r\n        {\r\n            \"id\": \"18\",\r\n            \"opening_at\": \"1975-09-14 05:24:51\",\r\n            \"description\": \"Id aliquid voluptas incidunt. Rem praesentium exercitationem molestiae quod facilis neque.\",\r\n            \"role_id\": \"18\",\r\n            \"role\": {\r\n                \"id\": \"18\",\r\n                \"name\": \"QA Engineer 4\",\r\n                \"code\": \"QAE\",\r\n                \"division_id\": \"1\"\r\n            }\r\n        },\r\n        {\r\n            \"id\": \"19\",\r\n            \"opening_at\": \"1979-01-26 12:54:39\",\r\n            \"description\": \"Minima repudiandae necessitatibus alias et. Doloribus suscipit velit voluptas dignissimos. Facilis rerum tenetur consequatur deserunt totam omnis.\",\r\n            \"role_id\": \"19\",\r\n            \"role\": {\r\n                \"id\": \"19\",\r\n                \"name\": \"QA Analyst 4\",\r\n                \"code\": \"QAA\",\r\n                \"division_id\": \"1\"\r\n            }\r\n        },\r\n        {\r\n            \"id\": \"20\",\r\n            \"opening_at\": \"1989-10-02 12:30:13\",\r\n            \"description\": \"Voluptas quis qui ut repellendus totam. Voluptas culpa illo qui. Laborum asperiores veniam neque vel beatae.\",\r\n            \"role_id\": \"20\",\r\n            \"role\": {\r\n                \"id\": \"20\",\r\n                \"name\": \"DevOps/SRE Engineer 4\",\r\n                \"code\": \"DEVOPS\",\r\n                \"division_id\": \"1\"\r\n            }\r\n        }\r\n    ],\r\n    \"first_page_url\": \"http://localhost:8088/api/v1/vacancies?page=1\",\r\n    \"from\": 16,\r\n    \"last_page\": 5,\r\n    \"last_page_url\": \"http://localhost:8088/api/v1/vacancies?page=5\",\r\n    \"links\": [],\r\n    \"next_page_url\": \"http://localhost:8088/api/v1/vacancies?page=5\",\r\n    \"path\": \"http://localhost:8088/api/v1/vacancies\",\r\n    \"per_page\": 5,\r\n    \"prev_page_url\": null,\r\n    \"to\": 20,\r\n    \"total\": 21\r\n}",
          "latency": 0,
          "statusCode": 200,
          "label": "",
          "headers": [],
          "filePath": "",
          "sendFileAsBody": false,
          "rules": [
            {
              "target": "query",
              "modifier": "page",
              "value": "4",
              "invert": false,
              "operator": "equals"
            }
          ],
          "rulesOperator": "OR",
          "disableTemplating": false,
          "fallbackTo404": false,
          "default": false
        },
        {
          "uuid": "d6a6461d-dc08-47c3-b35b-65cb086a5738",
          "body": "{\r\n    \"current_page\": 5,\r\n    \"data\": [\r\n        {\r\n            \"id\": \"21\",\r\n            \"opening_at\": \"2017-01-21 07:44:26\",\r\n            \"description\": \"Omnis fuga sed qui quisquam facere. Qui modi voluptatibus aut beatae dolorem adipisci voluptatem. Explicabo quis corrupti et officia non architecto. Rerum quas sed asperiores vel.\",\r\n            \"role_id\": \"21\",\r\n            \"role\": {\r\n                \"id\": \"21\",\r\n                \"name\": \"Senior Software Programmer - Backend Engineer 5\",\r\n                \"code\": \"SRBE\",\r\n                \"division_id\": \"1\"\r\n            }\r\n        }\r\n    ],\r\n    \"first_page_url\": \"http://localhost:8088/api/v1/vacancies?page=1\",\r\n    \"from\": 21,\r\n    \"last_page\": 5,\r\n    \"last_page_url\": \"http://localhost:8088/api/v1/vacancies?page=5\",\r\n    \"links\": [],\r\n    \"next_page_url\": \"\",\r\n    \"path\": \"http://localhost:8088/api/v1/vacancies\",\r\n    \"per_page\": 5,\r\n    \"prev_page_url\": null,\r\n    \"to\": 21,\r\n    \"total\": 21\r\n}",
          "latency": 0,
          "statusCode": 200,
          "label": "",
          "headers": [],
          "filePath": "",
          "sendFileAsBody": false,
          "rules": [
            {
              "target": "query",
              "modifier": "page",
              "value": "5",
              "invert": false,
              "operator": "equals"
            }
          ],
          "rulesOperator": "OR",
          "disableTemplating": false,
          "fallbackTo404": false,
          "default": false
        }
      ],
      "enabled": true,
      "responseMode": null
    },
    {
      "uuid": "e6bce05b-dac2-4254-859f-8c4d9f86ac6b",
      "documentation": "",
      "method": "get",
      "endpoint": "roles/:id",
      "responses": [
        {
          "uuid": "f8d1ab9f-ac9e-457c-82bb-a36e148e1c46",
          "body": "{\r\n    \"message\": \"\",\r\n    \"exception\": \"Symfony\\\\Component\\\\HttpKernel\\\\Exception\\\\NotFoundHttpException\",\r\n    \"file\": \"C:\\\\AMAN\\\\JDS\\\\DTRP\\\\digiteam-recruitment-app\\\\src\\\\vendor\\\\laravel\\\\framework\\\\src\\\\Illuminate\\\\Routing\\\\AbstractRouteCollection.php\",\r\n    \"line\": 44,\r\n    \"trace\": [\r\n        {\r\n            \"file\": \"C:\\\\AMAN\\\\JDS\\\\DTRP\\\\digiteam-recruitment-app\\\\src\\\\vendor\\\\laravel\\\\framework\\\\src\\\\Illuminate\\\\Routing\\\\RouteCollection.php\",\r\n            \"line\": 162,\r\n            \"function\": \"handleMatchedRoute\",\r\n            \"class\": \"Illuminate\\\\Routing\\\\AbstractRouteCollection\",\r\n            \"type\": \"->\"\r\n        },\r\n        {\r\n            \"file\": \"C:\\\\AMAN\\\\JDS\\\\DTRP\\\\digiteam-recruitment-app\\\\src\\\\vendor\\\\laravel\\\\framework\\\\src\\\\Illuminate\\\\Routing\\\\Router.php\",\r\n            \"line\": 680,\r\n            \"function\": \"match\",\r\n            \"class\": \"Illuminate\\\\Routing\\\\RouteCollection\",\r\n            \"type\": \"->\"\r\n        },\r\n        {\r\n            \"file\": \"C:\\\\AMAN\\\\JDS\\\\DTRP\\\\digiteam-recruitment-app\\\\src\\\\vendor\\\\laravel\\\\framework\\\\src\\\\Illuminate\\\\Routing\\\\Router.php\",\r\n            \"line\": 667,\r\n            \"function\": \"findRoute\",\r\n            \"class\": \"Illuminate\\\\Routing\\\\Router\",\r\n            \"type\": \"->\"\r\n        },\r\n        {\r\n            \"file\": \"C:\\\\AMAN\\\\JDS\\\\DTRP\\\\digiteam-recruitment-app\\\\src\\\\vendor\\\\laravel\\\\framework\\\\src\\\\Illuminate\\\\Routing\\\\Router.php\",\r\n            \"line\": 656,\r\n            \"function\": \"dispatchToRoute\",\r\n            \"class\": \"Illuminate\\\\Routing\\\\Router\",\r\n            \"type\": \"->\"\r\n        },\r\n        {\r\n            \"file\": \"C:\\\\AMAN\\\\JDS\\\\DTRP\\\\digiteam-recruitment-app\\\\src\\\\vendor\\\\laravel\\\\framework\\\\src\\\\Illuminate\\\\Foundation\\\\Http\\\\Kernel.php\",\r\n            \"line\": 167,\r\n            \"function\": \"dispatch\",\r\n            \"class\": \"Illuminate\\\\Routing\\\\Router\",\r\n            \"type\": \"->\"\r\n        },\r\n        {\r\n            \"file\": \"C:\\\\AMAN\\\\JDS\\\\DTRP\\\\digiteam-recruitment-app\\\\src\\\\vendor\\\\laravel\\\\framework\\\\src\\\\Illuminate\\\\Pipeline\\\\Pipeline.php\",\r\n            \"line\": 141,\r\n            \"function\": \"Illuminate\\\\Foundation\\\\Http\\\\{closure}\",\r\n            \"class\": \"Illuminate\\\\Foundation\\\\Http\\\\Kernel\",\r\n            \"type\": \"->\"\r\n        },\r\n        {\r\n            \"file\": \"C:\\\\AMAN\\\\JDS\\\\DTRP\\\\digiteam-recruitment-app\\\\src\\\\vendor\\\\laravel\\\\framework\\\\src\\\\Illuminate\\\\Foundation\\\\Http\\\\Middleware\\\\TransformsRequest.php\",\r\n            \"line\": 21,\r\n            \"function\": \"Illuminate\\\\Pipeline\\\\{closure}\",\r\n            \"class\": \"Illuminate\\\\Pipeline\\\\Pipeline\",\r\n            \"type\": \"->\"\r\n        },\r\n        {\r\n            \"file\": \"C:\\\\AMAN\\\\JDS\\\\DTRP\\\\digiteam-recruitment-app\\\\src\\\\vendor\\\\laravel\\\\framework\\\\src\\\\Illuminate\\\\Foundation\\\\Http\\\\Middleware\\\\ConvertEmptyStringsToNull.php\",\r\n            \"line\": 31,\r\n            \"function\": \"handle\",\r\n            \"class\": \"Illuminate\\\\Foundation\\\\Http\\\\Middleware\\\\TransformsRequest\",\r\n            \"type\": \"->\"\r\n        },\r\n        {\r\n            \"file\": \"C:\\\\AMAN\\\\JDS\\\\DTRP\\\\digiteam-recruitment-app\\\\src\\\\vendor\\\\laravel\\\\framework\\\\src\\\\Illuminate\\\\Pipeline\\\\Pipeline.php\",\r\n            \"line\": 180,\r\n            \"function\": \"handle\",\r\n            \"class\": \"Illuminate\\\\Foundation\\\\Http\\\\Middleware\\\\ConvertEmptyStringsToNull\",\r\n            \"type\": \"->\"\r\n        },\r\n        {\r\n            \"file\": \"C:\\\\AMAN\\\\JDS\\\\DTRP\\\\digiteam-recruitment-app\\\\src\\\\vendor\\\\laravel\\\\framework\\\\src\\\\Illuminate\\\\Foundation\\\\Http\\\\Middleware\\\\TransformsRequest.php\",\r\n            \"line\": 21,\r\n            \"function\": \"Illuminate\\\\Pipeline\\\\{closure}\",\r\n            \"class\": \"Illuminate\\\\Pipeline\\\\Pipeline\",\r\n            \"type\": \"->\"\r\n        },\r\n        {\r\n            \"file\": \"C:\\\\AMAN\\\\JDS\\\\DTRP\\\\digiteam-recruitment-app\\\\src\\\\vendor\\\\laravel\\\\framework\\\\src\\\\Illuminate\\\\Foundation\\\\Http\\\\Middleware\\\\TrimStrings.php\",\r\n            \"line\": 40,\r\n            \"function\": \"handle\",\r\n            \"class\": \"Illuminate\\\\Foundation\\\\Http\\\\Middleware\\\\TransformsRequest\",\r\n            \"type\": \"->\"\r\n        },\r\n        {\r\n            \"file\": \"C:\\\\AMAN\\\\JDS\\\\DTRP\\\\digiteam-recruitment-app\\\\src\\\\vendor\\\\laravel\\\\framework\\\\src\\\\Illuminate\\\\Pipeline\\\\Pipeline.php\",\r\n            \"line\": 180,\r\n            \"function\": \"handle\",\r\n            \"class\": \"Illuminate\\\\Foundation\\\\Http\\\\Middleware\\\\TrimStrings\",\r\n            \"type\": \"->\"\r\n        },\r\n        {\r\n            \"file\": \"C:\\\\AMAN\\\\JDS\\\\DTRP\\\\digiteam-recruitment-app\\\\src\\\\vendor\\\\laravel\\\\framework\\\\src\\\\Illuminate\\\\Foundation\\\\Http\\\\Middleware\\\\ValidatePostSize.php\",\r\n            \"line\": 27,\r\n            \"function\": \"Illuminate\\\\Pipeline\\\\{closure}\",\r\n            \"class\": \"Illuminate\\\\Pipeline\\\\Pipeline\",\r\n            \"type\": \"->\"\r\n        },\r\n        {\r\n            \"file\": \"C:\\\\AMAN\\\\JDS\\\\DTRP\\\\digiteam-recruitment-app\\\\src\\\\vendor\\\\laravel\\\\framework\\\\src\\\\Illuminate\\\\Pipeline\\\\Pipeline.php\",\r\n            \"line\": 180,\r\n            \"function\": \"handle\",\r\n            \"class\": \"Illuminate\\\\Foundation\\\\Http\\\\Middleware\\\\ValidatePostSize\",\r\n            \"type\": \"->\"\r\n        },\r\n        {\r\n            \"file\": \"C:\\\\AMAN\\\\JDS\\\\DTRP\\\\digiteam-recruitment-app\\\\src\\\\vendor\\\\laravel\\\\framework\\\\src\\\\Illuminate\\\\Foundation\\\\Http\\\\Middleware\\\\PreventRequestsDuringMaintenance.php\",\r\n            \"line\": 86,\r\n            \"function\": \"Illuminate\\\\Pipeline\\\\{closure}\",\r\n            \"class\": \"Illuminate\\\\Pipeline\\\\Pipeline\",\r\n            \"type\": \"->\"\r\n        },\r\n        {\r\n            \"file\": \"C:\\\\AMAN\\\\JDS\\\\DTRP\\\\digiteam-recruitment-app\\\\src\\\\vendor\\\\laravel\\\\framework\\\\src\\\\Illuminate\\\\Pipeline\\\\Pipeline.php\",\r\n            \"line\": 180,\r\n            \"function\": \"handle\",\r\n            \"class\": \"Illuminate\\\\Foundation\\\\Http\\\\Middleware\\\\PreventRequestsDuringMaintenance\",\r\n            \"type\": \"->\"\r\n        },\r\n        {\r\n            \"file\": \"C:\\\\AMAN\\\\JDS\\\\DTRP\\\\digiteam-recruitment-app\\\\src\\\\vendor\\\\fruitcake\\\\laravel-cors\\\\src\\\\HandleCors.php\",\r\n            \"line\": 52,\r\n            \"function\": \"Illuminate\\\\Pipeline\\\\{closure}\",\r\n            \"class\": \"Illuminate\\\\Pipeline\\\\Pipeline\",\r\n            \"type\": \"->\"\r\n        },\r\n        {\r\n            \"file\": \"C:\\\\AMAN\\\\JDS\\\\DTRP\\\\digiteam-recruitment-app\\\\src\\\\vendor\\\\laravel\\\\framework\\\\src\\\\Illuminate\\\\Pipeline\\\\Pipeline.php\",\r\n            \"line\": 180,\r\n            \"function\": \"handle\",\r\n            \"class\": \"Fruitcake\\\\Cors\\\\HandleCors\",\r\n            \"type\": \"->\"\r\n        },\r\n        {\r\n            \"file\": \"C:\\\\AMAN\\\\JDS\\\\DTRP\\\\digiteam-recruitment-app\\\\src\\\\vendor\\\\laravel\\\\framework\\\\src\\\\Illuminate\\\\Http\\\\Middleware\\\\TrustProxies.php\",\r\n            \"line\": 39,\r\n            \"function\": \"Illuminate\\\\Pipeline\\\\{closure}\",\r\n            \"class\": \"Illuminate\\\\Pipeline\\\\Pipeline\",\r\n            \"type\": \"->\"\r\n        },\r\n        {\r\n            \"file\": \"C:\\\\AMAN\\\\JDS\\\\DTRP\\\\digiteam-recruitment-app\\\\src\\\\vendor\\\\laravel\\\\framework\\\\src\\\\Illuminate\\\\Pipeline\\\\Pipeline.php\",\r\n            \"line\": 180,\r\n            \"function\": \"handle\",\r\n            \"class\": \"Illuminate\\\\Http\\\\Middleware\\\\TrustProxies\",\r\n            \"type\": \"->\"\r\n        },\r\n        {\r\n            \"file\": \"C:\\\\AMAN\\\\JDS\\\\DTRP\\\\digiteam-recruitment-app\\\\src\\\\vendor\\\\laravel\\\\framework\\\\src\\\\Illuminate\\\\Pipeline\\\\Pipeline.php\",\r\n            \"line\": 116,\r\n            \"function\": \"Illuminate\\\\Pipeline\\\\{closure}\",\r\n            \"class\": \"Illuminate\\\\Pipeline\\\\Pipeline\",\r\n            \"type\": \"->\"\r\n        },\r\n        {\r\n            \"file\": \"C:\\\\AMAN\\\\JDS\\\\DTRP\\\\digiteam-recruitment-app\\\\src\\\\vendor\\\\laravel\\\\framework\\\\src\\\\Illuminate\\\\Foundation\\\\Http\\\\Kernel.php\",\r\n            \"line\": 142,\r\n            \"function\": \"then\",\r\n            \"class\": \"Illuminate\\\\Pipeline\\\\Pipeline\",\r\n            \"type\": \"->\"\r\n        },\r\n        {\r\n            \"file\": \"C:\\\\AMAN\\\\JDS\\\\DTRP\\\\digiteam-recruitment-app\\\\src\\\\vendor\\\\laravel\\\\framework\\\\src\\\\Illuminate\\\\Foundation\\\\Http\\\\Kernel.php\",\r\n            \"line\": 111,\r\n            \"function\": \"sendRequestThroughRouter\",\r\n            \"class\": \"Illuminate\\\\Foundation\\\\Http\\\\Kernel\",\r\n            \"type\": \"->\"\r\n        },\r\n        {\r\n            \"file\": \"C:\\\\AMAN\\\\JDS\\\\DTRP\\\\digiteam-recruitment-app\\\\src\\\\public\\\\index.php\",\r\n            \"line\": 52,\r\n            \"function\": \"handle\",\r\n            \"class\": \"Illuminate\\\\Foundation\\\\Http\\\\Kernel\",\r\n            \"type\": \"->\"\r\n        },\r\n        {\r\n            \"file\": \"C:\\\\AMAN\\\\JDS\\\\DTRP\\\\digiteam-recruitment-app\\\\src\\\\server.php\",\r\n            \"line\": 21,\r\n            \"function\": \"require_once\"\r\n        }\r\n    ]\r\n}",
          "latency": 0,
          "statusCode": 404,
          "label": "",
          "headers": [],
          "filePath": "",
          "sendFileAsBody": false,
          "rules": [
            {
              "target": "params",
              "modifier": "id",
              "value": "",
              "invert": false,
              "operator": "null"
            },
            {
              "target": "params",
              "modifier": "id",
              "value": "^[0-9A-F]{8}-[0-9A-F]{4}-4[0-9A-F]{3}-[89AB][0-9A-F]{3}-[0-9A-F]{12}$",
              "invert": false,
              "operator": "regex"
            }
          ],
          "rulesOperator": "OR",
          "disableTemplating": false,
          "fallbackTo404": false,
          "default": true
        },
        {
          "uuid": "22804588-a621-44d8-b59b-d439db9f4ca9",
          "body": "{\r\n    \"id\": \"294c23c9-9db3-40e1-a148-d996773dd979\",\r\n    \"code\": \"JRBE\",\r\n    \"name\": \"Junior Software Programmer - Backend Engineer\",\r\n    \"description\": \"Jabar Digital Service sedang mencari talenta terbaik untuk posisi Software Programmer (Backend Engineer) yang memiliki passion dan kreatifitas dalam mengembangkan aplikasi web.\",\r\n    \"created_at\": \"2022-08-08T03:13:37.000000Z\",\r\n    \"updated_at\": \"2022-08-08T03:13:37.000000Z\",\r\n    \"division_id\": \"ce1bfe1b-4929-43e2-a78e-d10673f76116\",\r\n    \"responsibilities\": [\r\n        {\r\n            \"id\": \"e39b3c67-c426-4dbc-803c-f58a2835e1f8\",\r\n            \"description\": \"Full-time, bekerja di Jabar Command Center, Kantor Gubernur Jawa Barat, Gedung Sate.\",\r\n            \"order\": 1,\r\n            \"role_id\": \"294c23c9-9db3-40e1-a148-d996773dd979\",\r\n            \"created_at\": null,\r\n            \"updated_at\": null\r\n        },\r\n        {\r\n            \"id\": \"d8a055be-b636-4239-9ca1-31a5f6183766\",\r\n            \"description\": \"Memudahkan user menyelesaikan problem, dengan cara berkolaborasi dengan Software Architect, Frontend Engineer, Mobile Developer, dan Product Manager.\",\r\n            \"order\": 2,\r\n            \"role_id\": \"294c23c9-9db3-40e1-a148-d996773dd979\",\r\n            \"created_at\": null,\r\n            \"updated_at\": null\r\n        }\r\n    ],\r\n    \"skills\": [\r\n        {\r\n            \"id\": \"334102b9-44b5-40ca-b750-9d1a47bee9fc\",\r\n            \"description\": \"Kami menghargai skill dan pengalaman. Namun dengan kamu memiliki latar belakang pendidikan S1/S2 dari jurusan Teknik Informatika, Ilmu Komputer, Sistem Informasi, atau bidang lain yang relevan, akan sangat membantu memenuhi aspek administrasi.\",\r\n            \"order\": 1,\r\n            \"role_id\": \"294c23c9-9db3-40e1-a148-d996773dd979\",\r\n            \"created_at\": null,\r\n            \"updated_at\": null\r\n        },\r\n        {\r\n            \"id\": \"82177c1c-d7de-4d98-827c-c7af3ce1a713\",\r\n            \"description\": \"Seorang artisan. Coding adalah seni. Terbiasa mempraktekkan software craftsmanship (quality, well-crafted software). Maka diskusi clean code, clean architecture, adalah makanan sehari-hari tim saat proses code review. Bahkan naming variable adalah hal yan\",\r\n            \"order\": 2,\r\n            \"role_id\": \"294c23c9-9db3-40e1-a148-d996773dd979\",\r\n            \"created_at\": null,\r\n            \"updated_at\": null\r\n        },\r\n        {\r\n            \"id\": \"9cf5d642-f23f-4be5-b01d-126ba54e1241\",\r\n            \"description\": \"Menguasai salah satu bahasa pemrograman (PHP Laravel, NodeJS, Golang, Python).\",\r\n            \"order\": 3,\r\n            \"role_id\": \"294c23c9-9db3-40e1-a148-d996773dd979\",\r\n            \"created_at\": null,\r\n            \"updated_at\": null\r\n        },\r\n        {\r\n            \"id\": \"20431f43-6a51-41d6-b86d-bc63d0280a79\",\r\n            \"description\": \"Merancang basis data SQL (MySQL, PostgreSQL, dsb) dan NoSQL (MongoDB).\",\r\n            \"order\": 4,\r\n            \"role_id\": \"294c23c9-9db3-40e1-a148-d996773dd979\",\r\n            \"created_at\": null,\r\n            \"updated_at\": null\r\n        },\r\n        {\r\n            \"id\": \"02d519b6-30de-43af-8f24-07a2767ba778\",\r\n            \"description\": \"Bisa membedakan Response Code berikut: 200 OK, 401, 403, 404, 500.\",\r\n            \"order\": 5,\r\n            \"role_id\": \"294c23c9-9db3-40e1-a148-d996773dd979\",\r\n            \"created_at\": null,\r\n            \"updated_at\": null\r\n        },\r\n        {\r\n            \"id\": \"fd3c3b39-a6ae-43fd-8e11-2fca22566c89\",\r\n            \"description\": \"Mempunyai pengalaman melakukan deployment aplikasi secara modern (docker container, cloud) menjadi semakin menarik.\",\r\n            \"order\": 6,\r\n            \"role_id\": \"294c23c9-9db3-40e1-a148-d996773dd979\",\r\n            \"created_at\": null,\r\n            \"updated_at\": null\r\n        },\r\n        {\r\n            \"id\": \"17ab795a-2ac9-4714-9640-56532d04fb35\",\r\n            \"description\": \"Selalu penasaran untuk bisa menulis baris-baris kode yang clean yang bisa dipahami manusia. Bisa menulis dengan markdown juga.\",\r\n            \"order\": 7,\r\n            \"role_id\": \"294c23c9-9db3-40e1-a148-d996773dd979\",\r\n            \"created_at\": null,\r\n            \"updated_at\": null\r\n        },\r\n        {\r\n            \"id\": \"ec3d1fa6-30d4-4d52-9d17-cb0a6ac468d1\",\r\n            \"description\": \"Kurang percaya diri jika tidak membuat Unit Test atau Feature/API Test.\",\r\n            \"order\": 8,\r\n            \"role_id\": \"294c23c9-9db3-40e1-a148-d996773dd979\",\r\n            \"created_at\": null,\r\n            \"updated_at\": null\r\n        }\r\n    ]\r\n}",
          "latency": 0,
          "statusCode": 200,
          "label": "",
          "headers": [],
          "filePath": "",
          "sendFileAsBody": false,
          "rules": [
            {
              "target": "params",
              "modifier": "id",
              "value": "294c23c9-9db3-40e1-a148-d996773dd979",
              "invert": false,
              "operator": "equals"
            }
          ],
          "rulesOperator": "OR",
          "disableTemplating": false,
          "fallbackTo404": false,
          "default": false
        }
      ],
      "enabled": true,
      "responseMode": null
    }
  ],
  "proxyMode": false,
  "proxyHost": "",
  "proxyRemovePrefix": false,
  "tlsOptions": {
    "enabled": false,
    "type": "CERT",
    "pfxPath": "",
    "certPath": "",
    "keyPath": "",
    "caPath": "",
    "passphrase": ""
  },
  "cors": true,
  "headers": [
    {
      "key": "Content-Type",
      "value": "application/json"
    }
  ],
  "proxyReqHeaders": [
    {
      "key": "",
      "value": ""
    }
  ],
  "proxyResHeaders": [
    {
      "key": "",
      "value": ""
    }
  ]
}